{
  "andrew-carnegie": {
    "slug": "andrew-carnegie",
    "timeline": [
      {
        "year": "1848년",
        "event": "가족과 함께 스코틀랜드에서 미국으로 이민하여 펜실베이니아주 앨러게니에 정착했습니다."
      },
      {
        "year": "1865년",
        "event": "성장하고 있던 제철 산업 투자에 집중하기 위해 펜실베이니아 철도 회사를 떠났습니다."
      },
      {
        "year": "1889년",
        "event": "부유층이 자신의 부를 사회 발전에 사용해야 한다고 촉구한 영향력 있는 에세이 부의 복음을 출판했습니다."
      },
      {
        "year": "1892년",
        "event": "카네기 철강 회사를 설립하여 미국 철강 생산을 지배하는 산업 제국을 구축했습니다."
      },
      {
        "year": "1901년",
        "event": "자신의 철강 회사를 J.P. 모건에게 4억 8천만 달러에 매각하고 전업 자선가가 되었습니다."
      }
    ]
  },
  "edgar-allan-poe": {
    "slug": "edgar-allan-poe",
    "timeline": [
      {
        "year": "1809년",
        "event": "매사추세츠주 보스턴에서 태어난 직후 고아가 되어 앨런 가문에 거두어졌습니다."
      },
      {
        "year": "1827년",
        "event": "보스토니언이라는 필명으로 그의 첫 시집인 타메를란과 다른 시들을 출판했습니다."
      },
      {
        "year": "1841년",
        "event": "최초의 현대 추리 소설로 널리 인정받는 모르그가의 살인 사건을 발표했습니다."
      },
      {
        "year": "1845년",
        "event": "그의 시 갈가마귀를 출판하여 즉각적인 문학적 성공과 폭넓은 찬사를 받았습니다."
      },
      {
        "year": "1849년",
        "event": "볼티모어에서 40세의 나이로 아직까지 해명되지 않은 미스터리한 상황 속에 사망했습니다."
      }
    ]
  },
  "ernest-hemingway": {
    "slug": "ernest-hemingway",
    "timeline": [
      {
        "year": "1899",
        "event": "일리노이주 오크 파크에서 태어남."
      },
      {
        "year": "1913-1917",
        "event": "오크파크 앤드 리버포레스트 고등학교에 다님."
      },
      {
        "year": "1916",
        "event": "교내 신문 《더 트래피즈》에 첫 기사를 실음."
      },
      {
        "year": "1918",
        "event": "이탈리아 야전병원의 수송차 운전병으로 활약 중 박격포 공격으로 심한 부상을 입고 은성무공훈장을 받음."
      },
      {
        "year": "1919",
        "event": "미국으로 돌아왔으며, 《토론토 스타 위클리》에서 프리랜서 및 전속 작가로 일하기 시작함."
      },
      {
        "year": "1921",
        "event": "해들리 리처드슨과 결혼하고 파리로 이사하여 《토론토 스타》의 해외 특파원으로 일함."
      },
      {
        "year": "1922",
        "event": "실비아 비치의 서점 셰익스피어 앤드 컴퍼니에서 에즈라 파운드를 만남."
      },
      {
        "year": "1923",
        "event": "첫 책 《세 편의 단편과 열 편의 시》를 출판하고 아들 잭 헤밍웨이가 태어남."
      },
      {
        "year": "1925",
        "event": "《우리들의 시대에》를 출판하고 F. 스콧 피츠제럴드를 만남."
      },
      {
        "year": "1926",
        "event": "첫 소설 《태양은 다시 떠오른다》를 출판함."
      },
      {
        "year": "1927",
        "event": "해들리 리처드슨과 이혼 후 폴린 파이퍼와 재혼했으며, 단편집 《여자 없는 남자들》을 출판함."
      },
      {
        "year": "1928",
        "event": "아들 패트릭이 태어났으며, 아버지의 자살 소식을 들음."
      },
      {
        "year": "1929",
        "event": "소설 《무기여 잘 있거라》를 출판함."
      },
      {
        "year": "1930",
        "event": "교통사고로 오른팔이 부러짐."
      },
      {
        "year": "1931",
        "event": "세 번째 아들 그레고리 헤밍웨이가 태어남."
      },
      {
        "year": "1933",
        "event": "폴린과 케냐 사파리로 여행을 떠남."
      },
      {
        "year": "1934",
        "event": "낚싯배 필라 호를 사들임."
      },
      {
        "year": "1935",
        "event": "《아프리카의 푸른 언덕》을 출판함."
      },
      {
        "year": "1937",
        "event": "북아메리카 신문 연맹의 스페인 내전 보도를 맡기 위해 스페인으로 떠났으며, 《가진 자와 못 가진 자》를 출판함."
      },
      {
        "year": "1939",
        "event": "쿠바 아바나의 암보스문도스 호텔에 살기 시작함."
      },
      {
        "year": "1940",
        "event": "마사 겔혼과 결혼하고 소설 《누구를 위하여 종은 울리나》를 출판함."
      },
      {
        "year": "1941",
        "event": "마사와 함께 중국으로 감."
      },
      {
        "year": "1944-1945",
        "event": "런던과 유럽 등지에 머물렀으며, 노르망디 상륙 작전과 파리 해방 전투에 기자로 참여함."
      },
      {
        "year": "1945",
        "event": "마사 겔혼과 이혼함."
      },
      {
        "year": "1946",
        "event": "메리 웰시와 결혼함."
      },
      {
        "year": "1947",
        "event": "제2차 세계 대전 중의 용맹함을 인정받아 동성훈장을 수상함."
      },
      {
        "year": "1950",
        "event": "소설 《강 건너 숲속으로》를 출판함."
      },
      {
        "year": "1952",
        "event": "《노인과 바다》로 퓰리처상을 수상하고 두 번째 아프리카 여행을 떠남."
      },
      {
        "year": "1954",
        "event": "아프리카에서 두 차례 비행기 사고를 겪었으며, 노벨 문학상을 수상함."
      },
      {
        "year": "1959",
        "event": "쿠바를 떠나 아이다호주 케첨 외곽에 집을 구매함."
      },
      {
        "year": "1960",
        "event": "쿠바를 떠나 뉴욕으로 향했으며, 메이오 클리닉에 입원함."
      },
      {
        "year": "1961",
        "event": "메이오 클리닉에서 퇴원 후 케첨으로 돌아왔으며, 7월 2일 산탄총으로 스스로 목숨을 끊음."
      }
    ],
    "keyAchievements": [
      {
        "title": "문체 혁신",
        "description": "빙산 이론이라 불리는 간결하고 절제된 표현 방식으로 20세기 소설에 강한 영향을 미쳤습니다."
      },
      {
        "title": "노벨 문학상 수상",
        "description": "1954년에 노벨 문학상을 수상했습니다."
      },
      {
        "title": "퓰리처상 수상",
        "description": "1952년 《노인과 바다》로 퓰리처상을 수상했습니다."
      },
      {
        "title": "주요 작품 출판",
        "description": "《태양은 다시 떠오른다》(1926), 《무기여 잘 있거라》(1929), 《누구를 위하여 종은 울리나》(1940), 《노인과 바다》(1951) 등 다수의 대표작을 출판했습니다."
      },
      {
        "title": "동성훈장 수상",
        "description": "1947년 제2차 세계 대전 중의 용맹함을 인정받아 동성훈장을 수상했습니다."
      },
      {
        "title": "문학적 영향",
        "description": "미국 문학의 전반적인 문체에 큰 영향을 끼쳤으며, 2012년 시카고 문학 명예의 전당에 헌액되었습니다."
      }
    ],
    "faq": [
      {
        "question": "어니스트 헤밍웨이의 대표적인 문체는 무엇인가요?",
        "answer": "헤밍웨이는 '빙산 이론'이라 불리는 간결하고 절제된 표현 방식을 사용하여 20세기 소설에 큰 영향을 미쳤습니다."
      },
      {
        "question": "헤밍웨이는 언제 노벨 문학상을 수상했나요?",
        "answer": "헤밍웨이는 1954년에 노벨 문학상을 수상했습니다."
      },
      {
        "question": "헤밍웨이의 주요 작품으로는 어떤 것들이 있나요?",
        "answer": "그의 주요 작품으로는 《태양은 다시 떠오른다》, 《무기여 잘 있거라》, 《누구를 위하여 종은 울리나》, 《노인과 바다》 등이 있습니다."
      },
      {
        "question": "헤밍웨이는 어떻게 생을 마감했나요?",
        "answer": "1961년 7월 2일, 아이다호주 케첨에서 산탄총으로 스스로 목숨을 끊었습니다."
      },
      {
        "question": "헤밍웨이 작품의 주요 주제는 무엇인가요?",
        "answer": "그의 작품에는 사랑, 전쟁, 황야, 패배가 주요 주제로 등장하며, 자연은 부활과 휴식의 장소로 묘사됩니다."
      }
    ],
    "sourceVerified": true,
    "missingDataNote": ""
  },
  "henry-david-thoreau": {
    "slug": "henry-david-thoreau",
    "timeline": [
      {
        "year": "1837년",
        "event": "하버드 대학을 졸업하고 초월주의 동료인 랄프 왈도 에머슨과 평생의 우정을 시작했습니다."
      },
      {
        "year": "1845년",
        "event": "월든 호수 근처에 직접 지은 작은 오두막으로 이주하여 2년간의 소박한 삶의 실험을 시작했습니다."
      },
      {
        "year": "1846년",
        "event": "노예제와 멕시코-미국 전쟁에 항의하여 인두세 납부를 거부한 이유로 감옥에서 하룻밤을 보냈습니다."
      },
      {
        "year": "1849년",
        "event": "부당한 국가에 대한 비폭력 저항 철학을 명확히 한 에세이 시민 불복종을 출판했습니다."
      },
      {
        "year": "1854년",
        "event": "자연 속에서의 소박한 삶을 성찰한 그의 대표작 월든을 출판했습니다."
      }
    ]
  },
  "jp-morgan": {
    "slug": "jp-morgan",
    "timeline": [
      {
        "year": "1871년",
        "event": "안토니 드렉셀과 파트너십을 맺고 J.P. 모건 앤 컴퍼니의 전신인 드렉셀, 모건 앤 컴퍼니를 설립했습니다."
      },
      {
        "year": "1892년",
        "event": "에디슨 제너럴 일렉트릭과 톰슨-휴스턴 일렉트릭 컴퍼니의 합병을 주도하여 제너럴 일렉트릭을 설립했습니다."
      },
      {
        "year": "1895년",
        "event": "미국 재무부에 350만 온스의 금을 공급하는 신디케이트를 이끌어 경제를 안정시켰습니다."
      },
      {
        "year": "1901년",
        "event": "앤드류 카네기의 회사를 인수하여 세계 최초의 10억 달러 규모 기업인 미국 철강 회사(US 스틸)를 설립했습니다."
      },
      {
        "year": "1907년",
        "event": "1907년의 금융 공황을 막기 위해 다수의 주요 기관에 대한 금융 구제를 진두지휘했습니다."
      }
    ]
  },
  "ralph-waldo-emerson": {
    "slug": "ralph-waldo-emerson",
    "timeline": [
      {
        "year": "1803년",
        "event": "매사추세츠주 보스턴의 유니테리언 목사 가문에서 태어났습니다."
      },
      {
        "year": "1836년",
        "event": "미국 초월주의의 근본적인 철학적 신조를 세운 그의 첫 번째 에세이 자연을 출판했습니다."
      },
      {
        "year": "1837년",
        "event": "유럽으로부터의 지적 독립을 유명하게 촉구한 미국의 학자 연설을 했습니다."
      },
      {
        "year": "1841년",
        "event": "영향력 있는 에세이 자기 신뢰가 수록된 에세이 제1집을 출판했습니다."
      },
      {
        "year": "1844년",
        "event": "저명한 반노예제 연사로 부상하여 노예제 폐지 운동을 위해 활발하게 강연했습니다."
      }
    ]
  },
  "susan-b-anthony": {
    "slug": "susan-b-anthony",
    "timeline": [
      {
        "year": "1851년",
        "event": "엘리자베스 캐디 스탠턴을 만나 여성 권리 운동에서 강력하고 평생 지속되는 파트너십을 맺었습니다."
      },
      {
        "year": "1869년",
        "event": "여성 투표권을 위한 헌법 개정 확보에 헌신하는 전국 여성 참정권 협회를 공동 설립했습니다."
      },
      {
        "year": "1872년",
        "event": "수정 헌법 제14조를 시험하기 위해 뉴욕주 로체스터에서 열린 대통령 선거에서 투표했다가 체포되었습니다."
      },
      {
        "year": "1881년",
        "event": "스탠턴, 마틸다 조슬린 게이지와 함께 다권으로 구성된 여성 참정권의 역사를 출판하기 시작했습니다."
      },
      {
        "year": "1920년",
        "event": "그녀가 사망한 지 14년 후, 여성에게 투표권을 부여하는 수정 헌법 제19조가 비준되었으며, 이는 흔히 수잔 B. 앤서니 수정안으로 알려져 있습니다."
      }
    ]
  },
  "walt-whitman": {
    "slug": "walt-whitman",
    "timeline": [
      {
        "year": "1819년",
        "event": "뉴욕주 웨스트 힐스의 노동자 계급 가정에서 아홉 자녀 중 둘째로 태어났습니다."
      },
      {
        "year": "1855년",
        "event": "미국 시의 지형을 급격히 변화시킨 풀잎 초판을 자비로 출판했습니다."
      },
      {
        "year": "1862년",
        "event": "부상당한 형제를 돌보기 위해 워싱턴 D.C.로 여행을 갔으며, 이후 남북전쟁 기간 동안 자원 간호사로 일했습니다."
      },
      {
        "year": "1865년",
        "event": "미국 남북전쟁 당시의 경험을 반영한 깊은 감동을 주는 시집 드럼 탭스를 출판했습니다."
      },
      {
        "year": "1892년",
        "event": "뉴저지주 캠던에서 세상을 떠나기 직전 풀잎의 마지막 임종판을 준비했습니다."
      }
    ]
  },
  "max-planck": {
    "slug": "max-planck",
    "timeline": [
      {
        "year": "1858",
        "event": "홀슈타인의 킬에서 태어남."
      },
      {
        "year": "1864",
        "event": "제2차 슐레스비히 전쟁 중 킬로의 프로이센과 오스트리아 군대 행군을 목격함."
      },
      {
        "year": "1867",
        "event": "가족이 뮌헨으로 이사하고 막시밀리안 김나지움에 등록함."
      },
      {
        "year": "1874",
        "event": "뮌헨 대학교에서 연구를 시작함."
      },
      {
        "year": "1877",
        "event": "베를린의 프리드리히 빌헬름 대학교에서 1년 동안 연구함."
      },
      {
        "year": "1879",
        "event": "박사 학위 논문 '열역학 제2법칙에 관하여'를 방어함."
      },
      {
        "year": "1880",
        "event": "하빌리타치온 논문 '서로 다른 온도에서 등방성 물체의 평형 상태'를 발표하여 하빌리타치온을 획득함."
      },
      {
        "year": "1885",
        "event": "킬 대학교의 이론물리학 부교수로 임명됨."
      },
      {
        "year": "1887",
        "event": "마리 머르크와 결혼함."
      },
      {
        "year": "1889",
        "event": "베를린 프리드리히-빌헬름스-대학교의 키르히호프 직위를 계승하는 사람으로 임명됨."
      },
      {
        "year": "1892",
        "event": "정교수가 됨."
      },
      {
        "year": "1894",
        "event": "흑체 복사 문제에 관심을 돌림."
      },
      {
        "year": "1897",
        "event": "'열역학에 관한 논문'을 출판함."
      },
      {
        "year": "1898",
        "event": "독일 물리학회(DPG) 형성에 기여함."
      },
      {
        "year": "1900",
        "event": "에너지 양자화 가설을 포함한 플랑크 흑체 복사 법칙의 새로운 유도를 발표함."
      },
      {
        "year": "1905",
        "event": "독일 물리학회(DPG) 회장이 됨 (1909년까지)."
      },
      {
        "year": "1909",
        "event": "첫 번째 부인 마리 플랑크가 사망함."
      },
      {
        "year": "1911",
        "event": "두 번째 부인 마르가 폰 회슬린과 결혼함."
      },
      {
        "year": "1914",
        "event": "아인슈타인을 베를린으로 불러 새로운 교수직을 만들 수 있었음."
      },
      {
        "year": "1916",
        "event": "장남 카를이 베르됭 전투에서 전사함."
      },
      {
        "year": "1917",
        "event": "딸 그레테가 첫 아이를 낳다가 사망함."
      },
      {
        "year": "1918",
        "event": "에너지 양자의 발견으로 노벨 물리학상을 수상함 (실제 수상은 1919년)."
      },
      {
        "year": "1919",
        "event": "딸 엠마가 사망함."
      },
      {
        "year": "1920",
        "event": "프리츠 하버와 함께 독일 과학 비상기구(Notgemeinschaft der Deutschen Wissenschaft)를 설립함."
      },
      {
        "year": "1926",
        "event": "베를린에서 은퇴하고 에르빈 슈뢰딩거가 그의 뒤를 이음."
      },
      {
        "year": "1930",
        "event": "카이저 빌헬름 협회(KWG)의 회장이 됨."
      },
      {
        "year": "1933",
        "event": "나치가 집권했을 때 74세였으며, 히틀러와 유대인 교수 처우에 대해 논의함."
      },
      {
        "year": "1936",
        "event": "카이저 빌헬름 협회(KWG) 회장 임기가 끝남."
      },
      {
        "year": "1938",
        "event": "80세 생일을 맞았고, 프로이센 아카데미가 나치에 인수되자 회장직을 사임함."
      },
      {
        "year": "1944",
        "event": "베를린에 있는 그의 집이 공습으로 파괴되어 모든 과학 기록과 서신이 소실됨."
      },
      {
        "year": "1945",
        "event": "아들 에르빈이 히틀러 암살 시도에 가담했다는 이유로 처형됨."
      },
      {
        "year": "1947",
        "event": "괴팅겐에서 사망함."
      },
      {
        "year": "1948",
        "event": "카이저 빌헬름 협회가 막스 플랑크 협회(MPG)로 이름이 변경됨."
      }
    ],
    "keyAchievements": [
      {
        "title": "에너지 양자 발견",
        "description": "에너지 양자의 발견으로 1918년 노벨 물리학상을 수상했으며, 이는 원자 및 아원자 과정에 대한 이해에 혁명을 일으켰습니다."
      },
      {
        "title": "양자 이론의 창시",
        "description": "물리학자로서의 명성은 주로 양자 이론의 창시자로서의 역할에 있으며, 이는 고전 물리학과 양립할 수 없는 혁명적인 아이디어였습니다."
      },
      {
        "title": "플랑크 흑체 복사 법칙",
        "description": "흑체 복사 문제에 대한 연구를 통해 실험적으로 관찰된 흑체 스펙트럼을 잘 설명하는 플랑크 흑체 복사 법칙을 유도했습니다."
      },
      {
        "title": "플랑크 상수 (h)",
        "description": "전자기 에너지가 양자화된 형태로만 방출될 수 있다는 가설을 통해 플랑크 상수(h)를 도입하여 양자 이론의 근간을 마련했습니다."
      },
      {
        "title": "상대성 이론의 초기 인식 및 기여",
        "description": "알베르트 아인슈타인의 특수 상대성이론의 중요성을 즉시 인식한 몇 안 되는 사람 중 하나였으며, 이론을 재구성하는 데 기여했습니다."
      },
      {
        "title": "독일 과학 기관의 리더십",
        "description": "독일 물리학회(DPG) 회장과 카이저 빌헬름 협회(KWG) 회장을 역임하며 독일 과학계의 주요 직책을 수행했습니다."
      }
    ],
    "faq": [
      {
        "question": "막스 플랑크는 어떤 중요한 과학적 발견을 했나요?",
        "answer": "막스 플랑크는 에너지 양자를 발견하고 양자 이론을 창시하여 원자 및 아원자 과정에 대한 이해에 혁명을 일으켰습니다."
      },
      {
        "question": "막스 플랑크는 언제 노벨 물리학상을 수상했나요?",
        "answer": "그는 에너지 양자의 발견으로 1918년에 노벨 물리학상을 수상했으며, 실제 수상은 1919년에 이루어졌습니다."
      },
      {
        "question": "막스 플랑크는 나치 정권에 대해 어떤 입장을 취했나요?",
        "answer": "그는 유대인 동료들을 돕고 과학의 독립성을 지키려 노력했으며, 히틀러와 유대인 교수 처우에 대해 논의하고 프로이센 아카데미 회장직을 사임하며 나치에 항의했습니다."
      },
      {
        "question": "막스 플랑크의 종교적 견해는 어떠했나요?",
        "answer": "그는 독일 루터교 교인이었으며, 전능하고 전지전능하며 자비로운 신(반드시 인격적인 신은 아니더라도)을 믿었고, 과학과 종교 모두 '신을 향하여!'라는 목표를 가지고 있다고 보았습니다."
      }
    ],
    "sourceVerified": true,
    "missingDataNote": ""
  },
  "hypatia": {
    "slug": "hypatia",
    "timeline": [
      {
        "year": "355년경",
        "event": "알렉산드리아에서 철학자이자 기하학자인 테온의 딸로 태어남"
      },
      {
        "year": "415년",
        "event": "기독교인 폭도에게 살해당하고 주검이 훼손됨"
      }
    ],
    "keyAchievements": [
      {
        "title": "디오판토스의 천문학적 계산에 관한 저서",
        "description": "그녀의 저서 일부분이 15세기경 바티칸 도서관에서 발견되었습니다."
      },
      {
        "title": "디오판토스의 산술 해설서 저술",
        "description": "디오판토스의 풀이 외에 몇 가지 다른 풀이와 많은 새로운 문제를 해설서에 써넣어 연구업적으로 평가받습니다."
      },
      {
        "title": "아폴로니우스의 원추곡선 해설서 저술",
        "description": "아폴로니우스의 원추곡선에 대한 해설서를 저술했습니다."
      },
      {
        "title": "톨레미의 알마게스트 해설서 저술",
        "description": "톨레미의 대표작 알마게스트에 관한 해설서를 저술했습니다."
      },
      {
        "title": "유클리드 원론 해설서 공동 저술",
        "description": "아버지 테온과 공동으로 유클리드 원론에 관한 해설서를 저술했습니다."
      }
    ],
    "faq": [
      {
        "question": "히파티아는 어떤 인물이었나요?",
        "answer": "히파티아는 고대 이집트 알렉산드리아에서 활동한 신플라톤주의의 대표적인 그리스계 여성 철학자이자 수학자입니다."
      },
      {
        "question": "히파티아의 주요 저작은 무엇인가요?",
        "answer": "그녀는 디오판토스의 산술, 아폴로니우스의 원추곡선, 톨레미의 알마게스트에 대한 해설서를 썼으며, 아버지 테온과 유클리드 원론 해설서를 공동 저술했습니다."
      },
      {
        "question": "히파티아는 어떻게 죽었나요?",
        "answer": "대주교 키릴로스의 반대 세력으로 여겨져 기독교인 폭도에게 살해당하고 주검이 훼손되었습니다."
      },
      {
        "question": "히파티아의 아버지는 누구였나요?",
        "answer": "히파티아는 철학자이자 기하학자인 테온의 딸로 태어났습니다."
      }
    ],
    "sourceVerified": true,
    "missingDataNote": ""
  }
}