{
  "michael-faraday": {
    "timeline": [
      {
        "year": "1791",
        "event": "Born on September 22 as the third of four children to James Faraday and Margaret in Newington."
      },
      {
        "year": "1804",
        "event": "Became an apprentice to George Riebau, a bookseller, at the age of 13."
      },
      {
        "year": "1805",
        "event": "Signed a seven-year contract as George Riebau's apprentice on August 7."
      },
      {
        "year": "1806",
        "event": "Read Jane Marcet's 'Conversations on Chemistry' and the 3rd edition of the Encyclopædia Britannica by James Tytler."
      },
      {
        "year": "1809",
        "event": "Began taking notes on articles about art and science from newspapers and magazines."
      },
      {
        "year": "1812",
        "event": "Received tickets to Humphry Davy's chemistry lectures and attended them; wrote a letter asking Davy for help."
      },
      {
        "year": "1813",
        "event": "Started working at the Royal Institution in March; began a European tour as Davy's secretary and assistant on October 13."
      },
      {
        "year": "1814",
        "event": "Traveled to Naples, Italy, climbed Mount Vesuvius, and met Alessandro Volta in Pavia."
      },
      {
        "year": "1815",
        "event": "Returned to England on April 23; re-employed as superintendent and assistant of the apparatus and mineralogical collections at the Royal Institution's laboratory in May."
      },
      {
        "year": "1821",
        "event": "Married Sarah Barnard on June 12; published an article on electromagnetic rotation in 'Annals of Philosophy'."
      },
      {
        "year": "1822",
        "event": "Left the note 'Convert magnetism into electricity' in his laboratory notebook."
      },
      {
        "year": "1823",
        "event": "Successfully liquefied chlorine."
      },
      {
        "year": "1825",
        "event": "Discovered benzene; commissioned by the Royal Society to research the optical properties of glass used for telescopes."
      },
      {
        "year": "1826",
        "event": "Determined the molecular structure of naphthalene and created two sample crystals; established the 'Christmas Lectures for Children'."
      },
      {
        "year": "1827",
        "event": "Published a paper including practical guidance on chemistry in April; began optical glass experiments with a special furnace provided by the Royal Institution."
      },
      {
        "year": "1829",
        "event": "Announced the success of his optical glass research at the Bakerian Lecture of the Royal Society."
      },
      {
        "year": "1831",
        "event": "Began electromagnetic experiments on August 29 and discovered electromagnetic induction."
      },
      {
        "year": "1832",
        "event": "Began 'Electrochemical Decomposition' research at the end of the year and discovered Faraday's first law."
      },
      {
        "year": "1833",
        "event": "Experimented with various dissolved substances in a voltameter at the end of the year and discovered Faraday's second law."
      },
      {
        "year": "1836",
        "event": "Discovered that the charge on a charged conductor resides only on its exterior surface."
      },
      {
        "year": "1839",
        "event": "Published Volume 1 of 'Experimental Researches in Electricity'."
      },
      {
        "year": "1844",
        "event": "Successfully liquefied many substances including ammonia and carbon dioxide."
      },
      {
        "year": "1845",
        "event": "Met William Thomson at Cambridge University in June; discovered the Faraday effect on September 18, defining a physical relationship between magnetism and light."
      },
      {
        "year": "1848",
        "event": "Began experiments to investigate changes in diamagnetic materials influenced by magnets, and mentioned the concept of a magnetic field."
      },
      {
        "year": "1858",
        "event": "Granted residence in a house near Hampton Court along the River Thames in London at the request of Queen Victoria."
      },
      {
        "year": "1859",
        "event": "Published 'Experimental Researches in Chemistry and Physics'."
      },
      {
        "year": "1860",
        "event": "Submitted research results on gravity and electricity to the 'Philosophical Transactions' but was advised to withdraw them; gave a lecture on 'The Chemical History of a Candle' at the Royal Institution's Christmas Lectures."
      },
      {
        "year": "1861",
        "event": "Began suffering from memory loss symptoms; gave his final lecture at Christmas."
      },
      {
        "year": "1862",
        "event": "Conducted an experiment on whether the spectrum of sodium and other metals heated by a flame is affected by an electromagnetic field."
      },
      {
        "year": "1867",
        "event": "Passed away on August 25."
      }
    ],
    "keyAchievements": [
      {
        "title": "Discovery of Electromagnetic Induction",
        "description": "Discovered the principles of electromagnetic induction, diamagnetism, and the laws of electrolysis, and invented an electromagnetic rotary device that formed the foundation of the electric motor."
      },
      {
        "title": "Discovery of Benzene and Introduction of Chemical Terms",
        "description": "Discovered benzene as a chemist, investigated the clathrate hydrate of chlorine, and introduced technical terms such as anode, cathode, electrode, and ion for the first time."
      },
      {
        "title": "Successful Liquefaction of Gases",
        "description": "Successfully liquefied many substances such as chlorine, ammonia, and carbon dioxide, proving the existence of critical points and the interchangeability of states of matter."
      },
      {
        "title": "Research on Manufacturing Optical Glass",
        "description": "Researched the optical properties of glass used in telescopes and developed a method to produce uniform glass without bubbles or striae."
      },
      {
        "title": "Discovery of the Faraday Effect",
        "description": "Established the fundamental relationship between a magnetic field and light rays, showing that a magnetic field can affect light, and discovered the phenomenon of the plane of polarization rotating in a magnetic field."
      },
      {
        "title": "Classification of Magnetic Materials",
        "description": "Named diamagnetic materials that stop perpendicularly to a magnetic field and paramagnetic materials that stop parallel to it, discovering that most gases are diamagnetic while oxygen has paramagnetism."
      },
      {
        "title": "Introduction of the Magnetic Field Concept",
        "description": "Believed that lines of magnetic force had physical meaning and first mentioned the concept of a magnetic field, where the influence from two magnetic poles varies depending on the position."
      },
      {
        "title": "Discovery of the Faraday Cage Principle",
        "description": "Discovered that the electrical charge on a charged conductor resides only on its exterior and exerts no influence on anything enclosed within it."
      },
      {
        "title": "Creation of the Christmas Lectures",
        "description": "Created the 'Christmas Lectures for Children' in 1826 to popularize science, which has been passed down as a tradition of the Royal Institution in London."
      }
    ],
    "faq": [
      {
        "question": "What was Michael Faraday's educational background?",
        "answer": "Faraday received little formal or higher education during his childhood, learning only the basics of reading, writing, and arithmetic. He acquired his scientific knowledge primarily through self-study."
      },
      {
        "question": "Was Faraday proficient in mathematics?",
        "answer": "Faraday lacked mathematical skills to the point that he could only do simple algebra and could not handle trigonometry, but he excelled in visual thinking and imagination. His theories were later mathematically reformulated by James Clerk Maxwell."
      },
      {
        "question": "Did Faraday pursue fame or wealth?",
        "answer": "No. He was not interested in worldly wealth, refused to publish his lectures, and declined the presidency of the Royal Society as well as a knighthood. His humility and frugality stemmed from his religious beliefs."
      },
      {
        "question": "Did Faraday have children?",
        "answer": "No. Faraday married Sarah Barnard, but they had no children throughout their lives. However, he created and participated in science lectures for children, contributing to the popularization of science."
      },
      {
        "question": "How did Faraday's religion influence his scientific research?",
        "answer": "Faraday was a devout follower of Christian fundamentalism and a member of the Sandemanian congregation. His humility, frugality, and pure pursuit of academics were closely related to this religious background."
      }
    ]
  },
  "erwin-schrodinger": {
    "timeline": [
      {
        "year": "August 12, 1887",
        "event": "Born in Vienna, Austria."
      },
      {
        "year": "1910",
        "event": "Obtained a Ph.D. from the University of Vienna."
      },
      {
        "year": "April 6, 1920",
        "event": "Married Annemarie (Anny) Bertel."
      },
      {
        "year": "1921",
        "event": "Moved to the University of Zurich."
      },
      {
        "year": "January 1926",
        "event": "Published the paper 'Quantization as an Eigenvalue Problem' containing the Schrödinger equation."
      },
      {
        "year": "1927",
        "event": "Succeeded Max Planck at Friedrich Wilhelm University in Berlin."
      },
      {
        "year": "1933",
        "event": "Left Germany in opposition to Nazism."
      },
      {
        "year": "1933",
        "event": "Awarded the Nobel Prize in Physics along with Paul Dirac."
      },
      {
        "year": "1935",
        "event": "Proposed the Schrödinger's cat thought experiment."
      },
      {
        "year": "1938",
        "event": "Fired in Graz after the Austrian annexation, fled to Italy, and later relocated to Dublin."
      },
      {
        "year": "1940",
        "event": "Became the Director of the School for Theoretical Physics at the Dublin Institute for Advanced Studies."
      },
      {
        "year": "1944",
        "event": "Authored 'What Is Life?'."
      },
      {
        "year": "1948",
        "event": "Became a naturalized Irish citizen."
      },
      {
        "year": "1955",
        "event": "Retired in Dublin."
      },
      {
        "year": "1956",
        "event": "Returned to Vienna."
      },
      {
        "year": "January 4, 1961",
        "event": "Died of tuberculosis in Vienna at the age of 73."
      },
      {
        "year": "January 2022",
        "event": "The Department of Physics at Trinity College Dublin recommended removing his name from a lecture theatre considering his history of sexual abuse."
      }
    ],
    "keyAchievements": [
      {
        "title": "Development of the Schrödinger equation",
        "description": "Developed an equation providing a way to calculate a system's wave function and how it changes dynamically over time, thereby developing the fundamental results of quantum mechanics."
      },
      {
        "title": "Nobel Prize in Physics",
        "description": "Awarded the Nobel Prize in Physics in 1933 along with Paul Dirac for the formulation of the Schrödinger equation."
      },
      {
        "title": "Authored 'What Is Life?'",
        "description": "Viewed life phenomena from the perspective of physics and addressed the problem of genetics, inspiring the discovery of the DNA double helix structure."
      },
      {
        "title": "Proposed Schrödinger's cat thought experiment",
        "description": "A famous thought experiment designed to mock the Copenhagen interpretation of quantum mechanics, and one of his most enduring legacies."
      },
      {
        "title": "Research on unified field theory",
        "description": "Made several attempts to construct a unified field theory integrating gravity, electromagnetism, and nuclear forces."
      },
      {
        "title": "Research on color theory",
        "description": "Showed a strong interest in psychology, particularly color perception and colorimetry, and published a series of papers in this field."
      }
    ],
    "faq": [
      {
        "question": "For what achievement did Erwin Schrödinger win the Nobel Prize?",
        "answer": "He was awarded the Nobel Prize in Physics in 1933 along with Paul Dirac for the formulation of the Schrödinger equation."
      },
      {
        "question": "What is Schrödinger's cat?",
        "answer": "It is a famous thought experiment designed to mock the Copenhagen interpretation of quantum mechanics."
      },
      {
        "question": "What books did Schrödinger author?",
        "answer": "He authored 'What Is Life?', which includes discussions on the genetic code of living organisms and negentropy."
      },
      {
        "question": "When and where was Schrödinger born and when did he die?",
        "answer": "He was born in Vienna, Austria on August 12, 1887, and died of tuberculosis in Vienna on January 4, 1961, at the age of 73."
      },
      {
        "question": "Why did Schrödinger leave Germany?",
        "answer": "He left Germany in 1933 because he despised the anti-Semitism of the Nazis."
      }
    ]
  },
  "tran-hung-dao": {
    "timeline": [
      {
        "year": "1226",
        "event": "Birth of Tran Hung Dao, an imperial prince and general of the Tran dynasty in Great Viet"
      },
      {
        "year": "1257",
        "event": "When an envoy of the Mongol general Uriyangkhadai demanded safe passage through Vietnam, Tran Hung Dao was assigned the duty of border defense"
      },
      {
        "year": "1285",
        "event": "When Kublai Khan's son Toghon invaded Vietnam with an army of 500,000, Nhan Tong appointed Tran Hung Dao as the Commander-in-Chief to lead the army"
      },
      {
        "year": "1285",
        "event": "The army led by Tran Hung Dao fought against the Mongol forces, but the capital Thang Long was captured, and the retired emperor and Nhan Tong fled to Thanh Hoa"
      },
      {
        "year": "1285",
        "event": "Tran Hung Dao compiled the 'Binh thu yeu luoc' (Summary of Military Tactics) and wrote the 'Hich tuong si' (Proclamation to the Officers) to boost the troops' morale"
      },
      {
        "year": "June 1285",
        "event": "The army led by Tran Hung Dao recaptured Thang Long and forced Toghon's Mongol army to retreat"
      },
      {
        "year": "1287",
        "event": "When the Yuan dynasty's army invaded again, Tran Hung Dao withdrew his troops from Thang Long and annihilated the Yuan fleet at the Bach Dang River (Battle of Bach Dang)"
      },
      {
        "year": "1300",
        "event": "Tran Hung Dao died, leaving the last words: 'Unite the army like parents and children, treat the people generously, and use that strength to achieve great endeavors'"
      }
    ],
    "keyAchievements": [
      {
        "title": "Repelling Mongol Invasions",
        "description": "Successfully repelled massive invasions by the Yuan dynasty twice, in 1285 and 1287, safeguarding the independence of Vietnam."
      },
      {
        "title": "Military Strategy and Morale Boosting",
        "description": "Authored the 'Binh thu yeu luoc' and the 'Hich tuong si' to boost the morale of his soldiers and provide effective military strategies."
      },
      {
        "title": "Victory at the Battle of Bach Dang",
        "description": "Achieved a decisive victory in the Battle of Bach Dang in 1287 by using the strategy of planting wooden stakes in the riverbed to annihilate the Yuan fleet."
      }
    ],
    "faq": [
      {
        "question": "What is Tran Hung Dao's real name?",
        "answer": "Tran Hung Dao's real name is Tran Quoc Tuan, and Hung Dao is a title bestowed upon him later to praise his achievements."
      },
      {
        "question": "What books did Tran Hung Dao write?",
        "answer": "His works include 'Binh thu yeu luoc' (Summary of Military Tactics) and 'Van Kiep tong bi truyen thu' (Esoteric Manual of Van Kiep)."
      },
      {
        "question": "What is a famous statement made by Tran Hung Dao?",
        "answer": "During the Mongol invasion in 1285, he showed his will to fight by saying, 'If Your Majesty wishes to surrender, please cut off my head first'."
      }
    ]
  },
  "georges-cuvier": {
    "timeline": [
      {
        "year": "August 23, 1769",
        "event": "Born to a Protestant officer father in Montbeliard, Württemberg"
      },
      {
        "year": "May 13, 1832",
        "event": "Enrolled in the Caroline Academy (Karlsschule) in Stuttgart and spent 4 years"
      }
    ],
    "keyAchievements": [
      {
        "title": "Founded comparative anatomy",
        "description": "Earned the title of the 'Father of Comparative Anatomy' for establishing the foundation of comparative anatomy by systematically comparing the anatomical structures of various animals."
      },
      {
        "title": "Founded vertebrate paleontology",
        "description": "Established vertebrate paleontology by studying fossil bones and proposing the theory of extinction."
      },
      {
        "title": "Developed the principle of correlation of parts",
        "description": "Proposed the 'principle of correlation of parts', stating that the shape and function of each organ in an organism are closely linked to the overall structure and lifestyle of the animal."
      }
    ],
    "faq": [
      {
        "question": "What is Georges Cuvier's most famous achievement?",
        "answer": "He is the French zoologist known for founding comparative anatomy and paleontology."
      },
      {
        "question": "What is catastrophism advocated by Cuvier?",
        "answer": "It is the theory that sudden, widespread catastrophic events like massive floods occurred multiple times in Earth's past history, causing the extinction of species."
      },
      {
        "question": "What was Cuvier's view on evolution?",
        "answer": "He opposed the theory of evolution. According to his principle of correlation of parts, an organism's structure is perfectly adapted to its lifestyle, so he believed that changes in some parts would break the overall harmony, making survival impossible."
      },
      {
        "question": "How did Cuvier prove that extinction occurred?",
        "answer": "He proved that extinction was a real phenomenon by demonstrating that fossil elephant bones, like mammoths and mastodons, belonged to different species than living elephants."
      },
      {
        "question": "조르주 퀴비에는 파리 박물관에서 어떻게 교수가 되었나요?",
        "answer": "그는 생틸르의 소개로 파리 박물관의 교수가 되었습니다."
      }
    ]
  },
  "pythagoras": {
    "timeline": [
      {
        "year": "570 BC",
        "event": "Born on the island of Samos"
      },
      {
        "year": "532 BC",
        "event": "Traveled to various countries including Egypt, Phoenicia, and Chaldea after the age of 18 (unconfirmed)"
      },
      {
        "year": "530 BC",
        "event": "Moved to Croton in southern Italy and founded a religious organization and philosophical school"
      },
      {
        "year": "495 BC",
        "event": "With the rise of democratic politics in Croton, the Pythagorean order was violently suppressed"
      }
    ],
    "keyAchievements": [
      {
        "title": "Discovery of the Pythagorean Theorem",
        "description": "Proved the geometric theorem that the square of the hypotenuse is equal to the sum of the squares of the other two sides in a right-angled triangle."
      },
      {
        "title": "Belief that all things are numbers",
        "description": "Considered numbers to be the fundamental principle of the universe and emphasized their mathematical relationships and ratios."
      },
      {
        "title": "Mathematical theory of music",
        "description": "Discovered that harmonious musical scales form simple numerical ratios and applied this to the movement of the universe."
      },
      {
        "title": "Establishment of the Pythagorean School",
        "description": "Founded an exclusive religious and philosophical community centered around asceticism and mathematical exploration in Croton, southern Italy."
      },
      {
        "title": "Development of mathematical deductive methods",
        "description": "Elevated the practicality of mathematics to the realm of logical deduction and proof."
      }
    ],
    "faq": [
      {
        "question": "Who was Pythagoras?",
        "answer": "An ancient Greek philosopher and mathematician from Ionia, the founder of the Pythagorean school, widely known for discovering the Pythagorean theorem."
      },
      {
        "question": "Did Pythagoras actually discover the Pythagorean theorem?",
        "answer": "Although the theorem bears his name, it is unclear whether he himself proved it, and the content of the theorem was already known to the Babylonians."
      },
      {
        "question": "What were the main teachings of the Pythagorean school?",
        "answer": "They believed in the transmigration of souls (metempsychosis), practiced asceticism such as vegetarianism, and sought the fundamental harmony of the universe in numbers and their relationships."
      },
      {
        "question": "Why is it difficult to distinguish between the achievements of Pythagoras and those of his followers?",
        "answer": "Because the followers of the Pythagorean school attributed all discoveries to the founder Pythagoras, and kept their knowledge strictly secret."
      },
      {
        "question": "피타고라스는 어디에서 학파를 설립했나요?",
        "answer": "피타고라스는 남부 이탈리아의 크로토네로 이동하여 종교적인 학파를 세웠습니다."
      }
    ]
  }
}