{
  "slug": "lise-meitner",
  "timeline": [
    {
      "year": "1878",
      "event": "오스트리아 제국 빈 제2구에서 출생"
    },
    {
      "year": "1901",
      "event": "아카데미셰스 김나지움 졸업시험 통과"
    },
    {
      "year": "1907",
      "event": "알파입자 연구 논문을 피지칼리셰 차이트슈리프트에 제출"
    },
    {
      "year": "1908",
      "event": "루터교로 개종하고 기독교식 세례를 받음"
    },
    {
      "year": "1909",
      "event": "베타복사에 관한 논문 두 편을 게재"
    },
    {
      "year": "1912",
      "event": "카이저 빌헬름 학회(KWI)로 이동하여 오토 한의 방사화학 부서에서 무급으로 일함"
    },
    {
      "year": "1913",
      "event": "KWI의 정규직으로 채용됨"
    },
    {
      "year": "1917",
      "event": "오토 한과 함께 프로탁티늄의 안정적 이성질체를 최초로 발견하고 라이프니츠 메달을 수상함"
    },
    {
      "year": "1917",
      "event": "카이저 빌헬름 화학연구소에서 자기 연구실을 얻음"
    },
    {
      "year": "1922",
      "event": "원자의 내각전자가 방출되었을 때 외각전자가 내각을 채우면서 전후 에너지 차가 또 다른 외각전자로 전달되어 원자 밖으로 튕겨내는 현상을 밝혀냄"
    },
    {
      "year": "1926",
      "event": "베를린 대학교에서 물리학 정교수가 되어 독일 최초의 여성 정교수가 됨"
    },
    {
      "year": "1935",
      "event": "오토 한과 함께 '우라늄 너머 연구'를 시작함"
    },
    {
      "year": "1938",
      "event": "독일과 오스트리아가 합방(안슐루스)하면서 뉘른베르크 인종법의 적용 대상이 되어 처지가 위험해짐"
    },
    {
      "year": "1938",
      "event": "나치의 박해를 피해 베를린을 떠나 스웨덴으로 도피함"
    },
    {
      "year": "1939",
      "event": "오토 로베르트 프리슈와 함께 핵분열 연구 결과를 네이처에 게재함"
    },
    {
      "year": "1944",
      "event": "핵분열에 관한 노벨 화학상을 수상하지 못함"
    },
    {
      "year": "1947",
      "event": "시그반 연구소에서 퇴직하고 스웨덴 원자력위원회가 왕립 기술연구소에 새로 만든 연구실로 옮김"
    },
    {
      "year": "1949",
      "event": "스웨덴 시민권을 취득함"
    },
    {
      "year": "1960",
      "event": "완전히 은퇴하고 친지들이 대부분 살고 있는 영국으로 이주함"
    },
    {
      "year": "1968",
      "event": "수면 도중 사망함 (향년 89세)"
    },
    {
      "year": "1997",
      "event": "원자번호 109번 원소 마이트너륨이 리제 마이트너의 이름을 따서 명명됨"
    }
  ],
  "keyAchievements": [
    {
      "title": "핵분열 발견",
      "description": "오토 한과 함께 우라늄이 중성자를 흡수하면 핵분열을 일으킨다는 것을 처음으로 발견했습니다."
    },
    {
      "title": "핵분열 에너지 방출 원리 규명",
      "description": "오토 로베르트 프리슈와 함께 핵분열 시 질량 감손과 질량-에너지 등가에 따른 엄청난 에너지 방출이 수반될 것임을 깨달았습니다."
    },
    {
      "title": "프로탁티늄 안정적 이성질체 발견",
      "description": "오토 한과 함께 프로탁티늄의 안정적 이성질체를 최초로 발견했습니다."
    },
    {
      "title": "오제 효과 현상 규명",
      "description": "원자의 내각전자가 방출되었을 때 외각전자가 내각을 채우면서 전후 에너지 차가 또 다른 외각전자로 전달되어 원자 밖으로 튕겨내는 현상을 밝혀냈습니다."
    },
    {
      "title": "독일 최초 여성 정교수",
      "description": "베를린 대학교에서 물리학 정교수가 되어 독일 최초의 여성 정교수가 되었습니다."
    }
  ],
  "faq": [
    {
      "question": "리제 마이트너는 어떤 과학자였나요?",
      "answer": "유대계 오스트리아-스웨덴의 물리학자로, 방사능과 핵물리학을 전공했으며 오토 한과 함께 핵분열 발견에 중요한 기여를 했습니다."
    },
    {
      "question": "리제 마이트너는 노벨상을 받았나요?",
      "answer": "아니요, 1944년 핵분열에 관한 노벨 화학상은 오토 한이 단독 수상했으며, 마이트너는 수상하지 못했습니다."
    },
    {
      "question": "마이트너륨은 리제 마이트너의 이름을 딴 것인가요?",
      "answer": "네, 1997년 발견된 원자번호 109번 원소 마이트너륨은 리제 마이트너의 이름을 딴 것입니다."
    },
    {
      "question": "리제 마이트너는 핵무기 개발에 참여했나요?",
      "answer": "아니요, 맨해튼 프로젝트 참여 제안을 거부하며 '나는 폭탄 따위에 관해서 할 일이 없다!'고 선을 그었습니다."
    }
  ],
  "sourceVerified": true,
  "missingDataNote": ""
}